<?xml version="1.0" encoding="UTF-8" standalone="yes"?>
<mets xmlns:xsi="http://www.w3.org/2001/XMLSchema-instance" xmlns="http://www.loc.gov/METS/" xmlns:xlink="http://www.w3.org/1999/xlink" OBJID="rep1" LABEL="" TYPE="representation:MIXED" PROFILE="" xsi:schemaLocation="http://www.loc.gov/METS/ ../../schemas/IP.xsd http://www.w3.org/1999/xlink ../../schemas/xlink.xsd">
    <metsHdr CREATEDATE="2021-10-26T14:01:43.382+02:00" LASTMODDATE="2021-10-26T14:01:43.382+02:00" RECORDSTATUS="NEW"/>
    <amdSec ID="uuid-BCF9179D-7EE0-45DC-802A-9C52F0A89822"/>
    <fileSec ID="uuid-814C9BDC-CDB6-4AC0-8A8C-47E9A3D30352">
        <fileGrp ID="uuid-ED5A5061-21AF-452F-8BF8-A74231946DA1" USE="Common Specification files representation rep1">
            <fileGrp ID="uuid-C9D40F5B-C6DD-4F3A-8466-60CF769BC16B" USE="representations"/>
            <fileGrp ID="uuid-400A3EA9-FF42-4C38-9736-1A27ACA23F49" USE="data">
                <file ID="uuid-D1934A1D-CACC-4992-99B6-D3F0AC388FD4" MIMETYPE="image/jpeg" SIZE="120393" CREATED="2021-10-26T14:01:43.384+02:00" CHECKSUM="FF5757782916EE853AA5EFEB3C0D835D89F3CC2D55B6AA820CFBBF33D422A242" CHECKSUMTYPE="SHA-256">
                    <FLocat LOCTYPE="URL" xlink:type="simple" xlink:href="data%2FElectronics%2FEurorack%2FIMG-20200827-WA0000.jpg"/>
                </file>
                <file ID="uuid-02E9CFC0-938E-44EB-A80E-76FDED791B05" MIMETYPE="image/jpeg" SIZE="1454055" CREATED="2021-10-26T14:01:43.385+02:00" CHECKSUM="9ED7D492BEF3780FF86A5A707AE84672CF2BDA14F856A367C555D2B01311DBA0" CHECKSUMTYPE="SHA-256">
                    <FLocat LOCTYPE="URL" xlink:type="simple" xlink:href="data%2FElectronics%2FEurorack%2FIMG-20210204-WA0000.jpeg"/>
                </file>
                <file ID="uuid-0D2E17D9-B2EA-4319-B6CA-85D30BBC7E9C" MIMETYPE="application/pdf" SIZE="31880" CREATED="2021-10-26T14:01:43.386+02:00" CHECKSUM="F0C533E97A3B026F1DB6CEBEFD911716DF682AC4EA0C23894532BF47EFF42C21" CHECKSUMTYPE="SHA-256">
                    <FLocat LOCTYPE="URL" xlink:type="simple" xlink:href="data%2FElectronics%2FStaves%2F2695593.pdf"/>
                </file>
                <file ID="uuid-3BF6AFB7-AFE4-4910-9C20-F279E24BA71D" MIMETYPE="application/pdf" SIZE="2773" CREATED="2021-10-26T14:01:43.386+02:00" CHECKSUM="6C457C0C640C6C3CDD0E824C10833D585DC7FCE7C83BF2E37613162C5B6952F6" CHECKSUMTYPE="SHA-256">
                    <FLocat LOCTYPE="URL" xlink:type="simple" xlink:href="data%2FElectronics%2FStaves%2FA4_10_Stave_Blank_Manuscript.pdf"/>
                </file>
                <file ID="uuid-BE9576A3-5FE1-4370-9012-1124FBB32C08" MIMETYPE="application/pdf" SIZE="1018917" CREATED="2021-10-26T14:01:43.386+02:00" CHECKSUM="89AC6921E3F7B61F5424726BCDF5E469620E894CA9BC633030F8C2E14700CE5B" CHECKSUMTYPE="SHA-256">
                    <FLocat LOCTYPE="URL" xlink:type="simple" xlink:href="data%2FElectronics%2FPedals%2FEngineersThumb.pdf"/>
                </file>
                <file ID="uuid-8D0C3A01-D313-4E9E-AF4E-BB13F9DD58A3" MIMETYPE="application/pdf" SIZE="779823" CREATED="2021-10-26T14:01:43.387+02:00" CHECKSUM="BB6C35AFAEF2A65959514E282563F2B1190D0111A56C012D2CC10165C654BB13" CHECKSUMTYPE="SHA-256">
                    <FLocat LOCTYPE="URL" xlink:type="simple" xlink:href="data%2FElectronics%2FPedals%2FGlam2.pdf"/>
                </file>
                <file ID="uuid-206A83FC-97C2-4341-91CD-AB936DEF9387" MIMETYPE="application/vnd.openxmlformats-officedocument.wordprocessingml.document" SIZE="103372" CREATED="2021-10-26T14:01:43.387+02:00" CHECKSUM="98ECF92708C92E8E1FDCB508974358CCB2113BFE698429754EE42EF21775C9AA" CHECKSUMTYPE="SHA-256">
                    <FLocat LOCTYPE="URL" xlink:type="simple" xlink:href="data%2FElectronics%2FPedals%2FPedal+Transfers.docx"/>
                </file>
                <file ID="uuid-5E3FCBD8-50BD-406A-92E4-69DBEB65F96B" MIMETYPE="image/jpeg" SIZE="8054390" CREATED="2021-10-26T14:01:43.388+02:00" CHECKSUM="686FFC8F70860E7DC15E59C024FA4F1514626FD698E64C7C9D40EC9CB9243A57" CHECKSUMTYPE="SHA-256">
                    <FLocat LOCTYPE="URL" xlink:type="simple" xlink:href="data%2FElectronics%2FPedals%2FPedal_board.JPG"/>
                </file>
                <file ID="uuid-A5685A4D-D02D-4E1D-B7DA-7F0AFB157160" MIMETYPE="image/jpeg" SIZE="1525337" CREATED="2021-10-26T14:01:43.388+02:00" CHECKSUM="7832E6089549DFA7A8F1387500C5B5E4F6D77C05C8F977410768823F597E86A2" CHECKSUMTYPE="SHA-256">
                    <FLocat LOCTYPE="URL" xlink:type="simple" xlink:href="data%2FElectronics%2FPedals%2FPhaser.jpeg"/>
                </file>
                <file ID="uuid-CFF5D5D9-1E06-4839-91CB-1F86935D268B" MIMETYPE="application/pdf" SIZE="1033831" CREATED="2021-10-26T14:01:43.388+02:00" CHECKSUM="01FF709F0AFC22BAA391E02790DB367D699C909561C86391C1088FAD0B23C2B5" CHECKSUMTYPE="SHA-256">
                    <FLocat LOCTYPE="URL" xlink:type="simple" xlink:href="data%2FElectronics%2FPedals%2FP90-V2.pdf"/>
                </file>
                <file ID="uuid-3BDD913D-962A-4593-A958-70450CF3013F" MIMETYPE="application/pdf" SIZE="453023" CREATED="2021-10-26T14:01:43.389+02:00" CHECKSUM="901BB19FD2980ED252C40A960363D5D19C7A9A76CB032D06C14B20C75EA52770" CHECKSUMTYPE="SHA-256">
                    <FLocat LOCTYPE="URL" xlink:type="simple" xlink:href="data%2FElectronics%2FPedals%2FVerb-V2.pdf"/>
                </file>
                <file ID="uuid-76656A39-A26A-42A0-B011-3E495B2DE248" MIMETYPE="application/pdf" SIZE="715979" CREATED="2021-10-26T14:01:43.389+02:00" CHECKSUM="8160673AB9B387236CC9BAC673CAC1D02E51E33BECA6718A39D7E2F5572AE1BF" CHECKSUMTYPE="SHA-256">
                    <FLocat LOCTYPE="URL" xlink:type="simple" xlink:href="data%2FElectronics%2FPedals%2F3PDTDC.pdf"/>
                </file>
                <file ID="uuid-A4C2DF8E-3B56-4685-9456-DE40F23215E2" MIMETYPE="application/pdf" SIZE="731422" CREATED="2021-10-26T14:01:43.389+02:00" CHECKSUM="AAC992C413F2D1075054B24F7BECBCF6B0FD37C201162F5E5EB4ADEB7F58221B" CHECKSUMTYPE="SHA-256">
                    <FLocat LOCTYPE="URL" xlink:type="simple" xlink:href="data%2FElectronics%2FPedals%2FBigMuffPi.pdf"/>
                </file>
                <file ID="uuid-CB756D20-0EBD-449B-A4ED-51914292A76D" MIMETYPE="application/pdf" SIZE="341337" CREATED="2021-10-26T14:01:43.390+02:00" CHECKSUM="267B4394C4E4150210BA40D99F78428AA201D0646E37205149D4F560FB3A3D86" CHECKSUMTYPE="SHA-256">
                    <FLocat LOCTYPE="URL" xlink:type="simple" xlink:href="data%2FElectronics%2FPedals%2Fcreambuff.pdf"/>
                </file>
                <file ID="uuid-4F1B2094-A497-4CE3-97A6-1F9440ED61A7" MIMETYPE="application/pdf" SIZE="658241" CREATED="2021-10-26T14:01:43.390+02:00" CHECKSUM="D81C416889CEE050109DD7440681DD2C05933953DCDFC8B82D8D950446AF40B9" CHECKSUMTYPE="SHA-256">
                    <FLocat LOCTYPE="URL" xlink:type="simple" xlink:href="data%2FElectronics%2FAmplifiers%2FFender-57-Deluxe-Schematic.pdf"/>
                </file>
                <file ID="uuid-DB024D12-D9B5-42FB-9F8F-7605585C6891" MIMETYPE="application/pdf" SIZE="253451" CREATED="2021-10-26T14:01:43.391+02:00" CHECKSUM="93CDD2FFE90000701C845C0AE4F761980303544FE07E8227974955541249C1CF" CHECKSUMTYPE="SHA-256">
                    <FLocat LOCTYPE="URL" xlink:type="simple" xlink:href="data%2FElectronics%2FAmplifiers%2FFender-Bassman-5E6-Schematic.pdf"/>
                </file>
                <file ID="uuid-6933CA67-8EE8-466C-AE81-F0E7ED3DC602" MIMETYPE="application/pdf" SIZE="158072" CREATED="2021-10-26T14:01:43.391+02:00" CHECKSUM="EB1D8E59129463D7131314551288D2F66F6602EEB8DCED84CFDA9C31581D0B67" CHECKSUMTYPE="SHA-256">
                    <FLocat LOCTYPE="URL" xlink:type="simple" xlink:href="data%2FElectronics%2FAmplifiers%2FCarbon+Film+Resistors+0.5w.pdf"/>
                </file>
                <file ID="uuid-CF889724-FA0E-4DE2-B10C-289911024EFB" MIMETYPE="image/jpeg" SIZE="6422911" CREATED="2021-10-26T14:01:43.391+02:00" CHECKSUM="2268E0517F73F5385633F2EA2143B6F711686F34E78FCFEF2FDDD3B53BAF9F88" CHECKSUMTYPE="SHA-256">
                    <FLocat LOCTYPE="URL" xlink:type="simple" xlink:href="data%2FElectronics%2FAmplifiers%2FEvil_modular_preamp.JPG"/>
                </file>
                <file ID="uuid-1860A1E1-16FD-4039-8051-4BF39BD76323" MIMETYPE="application/pdf" SIZE="228660" CREATED="2021-10-26T14:01:43.392+02:00" CHECKSUM="733E5BC6D47F368CC2E765B45D0B7CC87E447E0632AA49727FD2251B7E4390AF" CHECKSUMTYPE="SHA-256">
                    <FLocat LOCTYPE="URL" xlink:type="simple" xlink:href="data%2FElectronics%2FAmplifiers%2FVox-AC30-1978-Schematic.pdf"/>
                </file>
                <file ID="uuid-CA07E851-4AD0-48A0-800F-6F45DDC7A74D" MIMETYPE="image/jpeg" SIZE="5337743" CREATED="2021-10-26T14:01:43.392+02:00" CHECKSUM="43B468145D76F44F4B3713CAD69F3B564779E26D71143BC98FF40422D0F9F207" CHECKSUMTYPE="SHA-256">
                    <FLocat LOCTYPE="URL" xlink:type="simple" xlink:href="data%2FElectronics%2FAmplifiers%2FEvil_prototype_preamp.JPG"/>
                </file>
                <file ID="uuid-A1AF2B52-CFEF-44B8-9F2A-3A0AFE3F207A" MIMETYPE="application/pdf" SIZE="188577" CREATED="2021-10-26T14:01:43.393+02:00" CHECKSUM="8F3A94D90F5720EBAAD9011EEC3F38201A0B2E6156F8E5091B82EB6F1F304964" CHECKSUMTYPE="SHA-256">
                    <FLocat LOCTYPE="URL" xlink:type="simple" xlink:href="data%2FElectronics%2FAmplifiers%2FVox-AC30-1986-Schematic.pdf"/>
                </file>
                <file ID="uuid-251B7846-27B9-4652-BEFC-DB16F20F71AE" MIMETYPE="image/jpeg" SIZE="3876182" CREATED="2021-10-26T14:01:43.393+02:00" CHECKSUM="35DB842679837248070A857ECC4EF569FD8B0D5FB34DBC5C81161A554BF47018" CHECKSUMTYPE="SHA-256">
                    <FLocat LOCTYPE="URL" xlink:type="simple" xlink:href="data%2FElectronics%2FAmplifiers%2FEurorack_preamp.jpeg"/>
                </file>
                <file ID="uuid-0ABC77EC-0BA3-424A-8943-F2B98CE77B12" MIMETYPE="application/pdf" SIZE="583889" CREATED="2021-10-26T14:01:43.393+02:00" CHECKSUM="E78A5E2606329410C6525A2CD187E3214FEA69BF33F3515995BD3EE229BE9632" CHECKSUMTYPE="SHA-256">
                    <FLocat LOCTYPE="URL" xlink:type="simple" xlink:href="data%2FElectronics%2FAmplifiers%2Fdatasheet.pdf"/>
                </file>
                <file ID="uuid-010FD59B-0CC6-4067-ADCF-7BFC373B0E67" MIMETYPE="application/pdf" SIZE="210123" CREATED="2021-10-26T14:01:43.394+02:00" CHECKSUM="4A4CC50FF64335E3936BD9D87C4A218F41AE7033113022327C45B4350AE337B6" CHECKSUMTYPE="SHA-256">
                    <FLocat LOCTYPE="URL" xlink:type="simple" xlink:href="data%2FElectronics%2FAmplifiers%2FHammond+Enclosures.pdf"/>
                </file>
                <file ID="uuid-8059A9F9-E1F4-41D7-A603-AB89FF515B21" MIMETYPE="application/pdf" SIZE="1417090" CREATED="2021-10-26T14:01:43.394+02:00" CHECKSUM="5047A26C513989615EC9AA3E3C8BFFC3D5C92A92F0884A2E3B502A3291E4ACC4" CHECKSUMTYPE="SHA-256">
                    <FLocat LOCTYPE="URL" xlink:type="simple" xlink:href="data%2FElectronics%2FAmplifiers%2FA100_DIY_Kit_1.pdf"/>
                </file>
                <file ID="uuid-DA687B79-9EAD-4FD5-B5CF-E0363EF23CE6" MIMETYPE="application/pdf" SIZE="111821" CREATED="2021-10-26T14:01:43.394+02:00" CHECKSUM="AD5C2DFB86AC1BDFD41BA3F73C2E339B14A39E8C0C86F6E8E31A02588315CA13" CHECKSUMTYPE="SHA-256">
                    <FLocat LOCTYPE="URL" xlink:type="simple" xlink:href="data%2FElectronics%2FAmplifiers%2Fecc803s-jj2005.pdf"/>
                </file>
                <file ID="uuid-4EB4EC4F-6D89-4424-8ECA-D92074C13423" MIMETYPE="application/pdf" SIZE="392274" CREATED="2021-10-26T14:01:43.395+02:00" CHECKSUM="0CDB4B2610A05F1C1C3769ADE510B5812E9C9FBE0568055A61533F6A0C1725E2" CHECKSUMTYPE="SHA-256">
                    <FLocat LOCTYPE="URL" xlink:type="simple" xlink:href="data%2FElectronics%2FAmplifiers%2FEnclosure.pdf"/>
                </file>
            </fileGrp>
            <fileGrp ID="uuid-F7ED97CB-8DAE-4A34-9CAB-D8438AD37C97" USE="schemas"/>
            <fileGrp ID="uuid-841DA68F-4D52-4177-86DF-C66008F7C98A" USE="submission"/>
            <fileGrp ID="uuid-35EA6CB8-DEB0-4FAB-806D-E4E3FD557F6E" USE="documentation"/>
        </fileGrp>
    </fileSec>
    <structMap ID="uuid-8DAE8155-08D5-48DA-9715-778F39D02929" TYPE="physical" LABEL="Common Specification structural map">
        <div ID="uuid-4170FD21-E2C9-4940-9C8C-A91D0CD2254A" TYPE="ORIGINAL" LABEL="rep1">
            <div ID="uuid-53E4FE5A-CAEC-4C23-8F03-54AA41ACAA5A" LABEL="metadata">
                <div ID="uuid-CD2ECBE8-4FF8-437B-81AD-8B29941D770E" LABEL="descriptive"/>
                <div ID="uuid-5AE9394D-EC2D-4B46-920E-C9B5CFA5508D" LABEL="preservation"/>
                <div ID="uuid-22A12D02-682C-4256-B6A1-2020675B2EED" LABEL="other"/>
            </div>
            <div ID="uuid-0D713283-CCF2-421C-A2ED-C03F7C3CC16E" LABEL="representations"/>
            <div ID="uuid-61A3807B-0E13-459F-9C69-527787D56603" LABEL="data">
                <fptr FILEID="uuid-D1934A1D-CACC-4992-99B6-D3F0AC388FD4"/>
                <fptr FILEID="uuid-02E9CFC0-938E-44EB-A80E-76FDED791B05"/>
                <fptr FILEID="uuid-0D2E17D9-B2EA-4319-B6CA-85D30BBC7E9C"/>
                <fptr FILEID="uuid-3BF6AFB7-AFE4-4910-9C20-F279E24BA71D"/>
                <fptr FILEID="uuid-BE9576A3-5FE1-4370-9012-1124FBB32C08"/>
                <fptr FILEID="uuid-8D0C3A01-D313-4E9E-AF4E-BB13F9DD58A3"/>
                <fptr FILEID="uuid-206A83FC-97C2-4341-91CD-AB936DEF9387"/>
                <fptr FILEID="uuid-5E3FCBD8-50BD-406A-92E4-69DBEB65F96B"/>
                <fptr FILEID="uuid-A5685A4D-D02D-4E1D-B7DA-7F0AFB157160"/>
                <fptr FILEID="uuid-CFF5D5D9-1E06-4839-91CB-1F86935D268B"/>
                <fptr FILEID="uuid-3BDD913D-962A-4593-A958-70450CF3013F"/>
                <fptr FILEID="uuid-76656A39-A26A-42A0-B011-3E495B2DE248"/>
                <fptr FILEID="uuid-A4C2DF8E-3B56-4685-9456-DE40F23215E2"/>
                <fptr FILEID="uuid-CB756D20-0EBD-449B-A4ED-51914292A76D"/>
                <fptr FILEID="uuid-4F1B2094-A497-4CE3-97A6-1F9440ED61A7"/>
                <fptr FILEID="uuid-DB024D12-D9B5-42FB-9F8F-7605585C6891"/>
                <fptr FILEID="uuid-6933CA67-8EE8-466C-AE81-F0E7ED3DC602"/>
                <fptr FILEID="uuid-CF889724-FA0E-4DE2-B10C-289911024EFB"/>
                <fptr FILEID="uuid-1860A1E1-16FD-4039-8051-4BF39BD76323"/>
                <fptr FILEID="uuid-CA07E851-4AD0-48A0-800F-6F45DDC7A74D"/>
                <fptr FILEID="uuid-A1AF2B52-CFEF-44B8-9F2A-3A0AFE3F207A"/>
                <fptr FILEID="uuid-251B7846-27B9-4652-BEFC-DB16F20F71AE"/>
                <fptr FILEID="uuid-0ABC77EC-0BA3-424A-8943-F2B98CE77B12"/>
                <fptr FILEID="uuid-010FD59B-0CC6-4067-ADCF-7BFC373B0E67"/>
                <fptr FILEID="uuid-8059A9F9-E1F4-41D7-A603-AB89FF515B21"/>
                <fptr FILEID="uuid-DA687B79-9EAD-4FD5-B5CF-E0363EF23CE6"/>
                <fptr FILEID="uuid-4EB4EC4F-6D89-4424-8ECA-D92074C13423"/>
            </div>
            <div ID="uuid-B1147467-72C7-4419-AD07-48F259DC4F88" LABEL="schemas"/>
            <div ID="uuid-04ADAE47-679A-4BC3-99D6-C36C8E02B59E" LABEL="documentation"/>
            <div ID="uuid-C578CAAD-B08B-484E-A332-0E1109276725" LABEL="submission"/>
        </div>
    </structMap>
</mets>
